rytrme_api_python/__init__.py
rytrme_api_python/rytrme_api_python.py
rytrme_api_python-1.0.2.dist-info/METADATA
rytrme_api_python-1.0.2.dist-info/WHEEL
rytrme_api_python-1.0.2.dist-info/top_level.txt
rytrme_api_python-1.0.2.dist-info/RECORD
