Metadata-Version: 2.1
Name: rytrme-api-python
Version: 1.0.2
Summary: Easy way to handle the rytrme API with python
Home-page: https://github.com/WiktorBoro/rytrme-api-python
Author: Wiktor Borowicz
Author-email: w.borowicz4@gmail.com
Classifier: Programming Language :: Python :: 3
Classifier: License :: OSI Approved :: MIT License
Classifier: Operating System :: OS Independent
Requires-Python: >=3.6
Requires-Dist: requests
